eradiate/__init__.py
eradiate/__init__.pyi
eradiate/_factory.py
eradiate/_mode.py
eradiate/_version.py
eradiate/attrs.py
eradiate/cfconventions.py
eradiate/constants.py
eradiate/contexts.py
eradiate/converters.py
eradiate/exceptions.py
eradiate/frame.py
eradiate/plot.mplstyle
eradiate/plot.py
eradiate/py.typed
eradiate/quad.py
eradiate/rng.py
eradiate/srf_tools.py
eradiate/tutorials.py
eradiate/typing.py
eradiate/units.py
eradiate/units.txt
eradiate/validators.py
eradiate/warp.py
eradiate/cli/__init__.py
eradiate/cli/_console.py
eradiate/cli/data.py
eradiate/cli/srf.py
eradiate/cli/sys_info.py
eradiate/config/__init__.py
eradiate/config/__init__.pyi
eradiate/config/_defaults.py
eradiate/config/_settings.py
eradiate/config/eradiate.toml
eradiate/data/__init__.py
eradiate/data/__init__.pyi
eradiate/data/_asset_manager.py
eradiate/data/_file_resolver.py
eradiate/data/_validation.py
eradiate/data/io.py
eradiate/data/resources.yml
eradiate/data/schemas/__init__.py
eradiate/data/schemas/particle_dataset_v1.yml
eradiate/data/schemas/srf_v1.yml
eradiate/experiments/__init__.py
eradiate/experiments/__init__.pyi
eradiate/experiments/_atmosphere.py
eradiate/experiments/_canopy.py
eradiate/experiments/_canopy_atmosphere.py
eradiate/experiments/_core.py
eradiate/experiments/_dem.py
eradiate/experiments/_helpers.py
eradiate/kernel/__init__.py
eradiate/kernel/__init__.pyi
eradiate/kernel/_bitmap.py
eradiate/kernel/_bsdf.py
eradiate/kernel/_kernel_dict.py
eradiate/kernel/_render.py
eradiate/kernel/_versions.py
eradiate/kernel/gridvolume.py
eradiate/kernel/logging.py
eradiate/kernel/transform.py
eradiate/notebook/__init__.py
eradiate/notebook/__init__.pyi
eradiate/notebook/tutorials.py
eradiate/pipelines/__init__.py
eradiate/pipelines/__init__.pyi
eradiate/pipelines/core.py
eradiate/pipelines/logic.py
eradiate/pipelines/definitions/__init__.py
eradiate/pipelines/definitions/__init__.pyi
eradiate/pipelines/definitions/core.py
eradiate/radprops/__init__.py
eradiate-1.0.1.dist-info/licenses/LICENSE
eradiate-1.0.1.dist-info/METADATA
eradiate-1.0.1.dist-info/WHEEL
eradiate-1.0.1.dist-info/entry_points.txt
eradiate-1.0.1.dist-info/top_level.txt
eradiate-1.0.1.dist-info/RECORD
