Metadata-Version: 2.4
Name: eradiate
Version: 1.0.1
Summary: A radiative transfer model for the Earth observation community
Author: The Eradiate Team
Maintainer: The Eradiate Team
License: LGPLv3
Project-URL: changelog, https://github.com/eradiate/eradiate/CHANGELOG.md
Project-URL: documentation, https://eradiate.readthedocs.io
Project-URL: repository, https://github.com/eradiate/eradiate
Requires-Python: <3.13,>=3.9
License-File: LICENSE
Requires-Dist: aenum
Requires-Dist: attrs>=22.2
Requires-Dist: cachetools>=5.3
Requires-Dist: cerberus>=1.3
Requires-Dist: click
Requires-Dist: dessinemoi>=23.1.0
Requires-Dist: dynaconf>=3.2
Requires-Dist: joseki>=2.6.0
Requires-Dist: lazy_loader>=0.1
Requires-Dist: matplotlib>=3.3
Requires-Dist: netcdf4
Requires-Dist: numpy<2
Requires-Dist: pint
Requires-Dist: pinttrs>=23.2.0
Requires-Dist: pooch
Requires-Dist: rich
Requires-Dist: ruamel.yaml
Requires-Dist: scipy
Requires-Dist: sf-hamilton>=1.40
Requires-Dist: typer>=0.9.0
Requires-Dist: tqdm
Requires-Dist: shellingham!=1.5.1
Requires-Dist: xarray!=0.20.*,<2025,>=0.19
Provides-Extra: kernel
Requires-Dist: eradiate-mitsuba==0.3.2; extra == "kernel"
Provides-Extra: recommended
Requires-Dist: aabbtree; extra == "recommended"
Requires-Dist: astropy; extra == "recommended"
Requires-Dist: ipython; extra == "recommended"
Requires-Dist: ipywidgets; extra == "recommended"
Requires-Dist: jupyterlab; extra == "recommended"
Requires-Dist: python-dateutil; extra == "recommended"
Requires-Dist: graphviz; extra == "recommended"
Requires-Dist: seaborn; extra == "recommended"
Dynamic: license-file
